awscli_profile-1.1.0.dist-info/METADATA
awscli_profile-1.1.0.dist-info/WHEEL
awscli_profile-1.1.0.dist-info/entry_points.txt
awscli_profile/__init__.py
awscli_profile/__main__.py
awscli_profile-1.1.0.dist-info/RECORD
