Metadata-Version: 2.1
Name: awscli-profile
Version: 1.1.0
Summary: awscli profile manager intended for use as cli alias
Author-Email: Yuichiro Smith <yu-ichiro@s3i7h.com>
License: MIT
Project-URL: Homepage, https://github.com/s3i7h/awscli-profile
Project-URL: Repository, https://github.com/s3i7h/awscli-profile
Project-URL: Issues, https://github.com/s3i7h/awscli-profile/issues
Requires-Python: >=3.8
Requires-Dist: typer>=0.12.4
